alibabacloud_aligenieip_1_0/__init__.py
alibabacloud_aligenieip_1_0/client.py
alibabacloud_aligenieip_1_0/models/__init__.py
alibabacloud_aligenieip_1_0/models/_add_cartoon_headers.py
alibabacloud_aligenieip_1_0/models/_add_cartoon_request.py
alibabacloud_aligenieip_1_0/models/_add_cartoon_response.py
alibabacloud_aligenieip_1_0/models/_add_cartoon_response_body.py
alibabacloud_aligenieip_1_0/models/_add_custom_qaheaders.py
alibabacloud_aligenieip_1_0/models/_add_custom_qarequest.py
alibabacloud_aligenieip_1_0/models/_add_custom_qaresponse.py
alibabacloud_aligenieip_1_0/models/_add_custom_qaresponse_body.py
alibabacloud_aligenieip_1_0/models/_add_custom_qashrink_request.py
alibabacloud_aligenieip_1_0/models/_add_custom_qav2headers.py
alibabacloud_aligenieip_1_0/models/_add_custom_qav2request.py
alibabacloud_aligenieip_1_0/models/_add_custom_qav2response.py
alibabacloud_aligenieip_1_0/models/_add_custom_qav2response_body.py
alibabacloud_aligenieip_1_0/models/_add_custom_qav2shrink_request.py
alibabacloud_aligenieip_1_0/models/_add_message_template_headers.py
alibabacloud_aligenieip_1_0/models/_add_message_template_request.py
alibabacloud_aligenieip_1_0/models/_add_message_template_response.py
alibabacloud_aligenieip_1_0/models/_add_message_template_response_body.py
alibabacloud_aligenieip_1_0/models/_add_or_update_dis_play_modes_headers.py
alibabacloud_aligenieip_1_0/models/_add_or_update_dis_play_modes_request.py
alibabacloud_aligenieip_1_0/models/_add_or_update_dis_play_modes_response.py
alibabacloud_aligenieip_1_0/models/_add_or_update_dis_play_modes_response_body.py
alibabacloud_aligenieip_1_0/models/_add_or_update_dis_play_modes_shrink_request.py
alibabacloud_aligenieip_1_0/models/_add_or_update_hotel_setting_headers.py
alibabacloud_aligenieip_1_0/models/_add_or_update_hotel_setting_request.py
alibabacloud_aligenieip_1_0/models/_add_or_update_hotel_setting_response.py
alibabacloud_aligenieip_1_0/models/_add_or_update_hotel_setting_response_body.py
alibabacloud_aligenieip_1_0-2.8.4.dist-info/LICENSE
alibabacloud_aligenieip_1_0-2.8.4.dist-info/METADATA
alibabacloud_aligenieip_1_0-2.8.4.dist-info/WHEEL
alibabacloud_aligenieip_1_0-2.8.4.dist-info/top_level.txt
alibabacloud_aligenieip_1_0-2.8.4.dist-info/RECORD
